{
  "id": "B0878ZHGQQ",
  "title": "Lamincoa Womens Air Running Shoes Lightweight Women Sneakers Air Cushion Walking Tennis Shoes for Women",
  "description": null,
  "images": [
    [
      "https://m.media-amazon.com/images/I/81uS0LrDBXL._AC_UY695_.jpg",
      "https://m.media-amazon.com/images/I/81uS0LrDBXL._AC_UY500_.jpg",
      "https://m.media-amazon.com/images/I/81uS0LrDBXL._AC_UY575_.jpg",
      "https://m.media-amazon.com/images/I/81uS0LrDBXL._AC_UY625_.jpg",
      "https://m.media-amazon.com/images/I/81uS0LrDBXL._AC_UY395_.jpg",
      "https://m.media-amazon.com/images/I/81uS0LrDBXL._AC_UY675_.jpg",
      "https://m.media-amazon.com/images/I/81uS0LrDBXL._AC_UY535_.jpg"
    ]
  ],
  "rating": 4.2,
  "reviews_count": 9366,
  "reviews_link": "https://www.amazon.com/Lamincoa-Athletic-Sneakers-Lightweight-Breathable/product-reviews/B0878ZHGQQ/ref=cm_cr_dp_d_show_all_btm?ie=UTF8&reviewerType=all_reviews",
  "price_range": {
    "from": 42.85,
    "to": 43.85
  },
  "variants": [
    {
      "url": "https://www.amazon.com/dp/B0878TG9DT/ref=twister_B0878ZHGQQ",
      "id": "B0878TG9DT"
    },
    {
      "url": "https://www.amazon.com/dp/B08CXJ14TQ/ref=twister_B0878ZHGQQ",
      "id": "B08CXJ14TQ"
    },
    {
      "url": "https://www.amazon.com/dp/B08JH3KJKZ/ref=twister_B0878ZHGQQ",
      "id": "B08JH3KJKZ"
    },
    {
      "url": "https://www.amazon.com/dp/B08JGQGCSX/ref=twister_B0878ZHGQQ",
      "id": "B08JGQGCSX"
    },
    {
      "url": "https://www.amazon.com/dp/B08JDVBF62/ref=twister_B0878ZHGQQ",
      "id": "B08JDVBF62"
    },
    {
      "url": "https://www.amazon.com/dp/B08CXRX6MV/ref=twister_B0878ZHGQQ",
      "id": "B08CXRX6MV"
    },
    {
      "url": "https://www.amazon.com/dp/B08CXQ6P1G/ref=twister_B0878ZHGQQ",
      "id": "B08CXQ6P1G"
    },
    {
      "url": "https://www.amazon.com/dp/B08JG269BP/ref=twister_B0878ZHGQQ",
      "id": "B08JG269BP"
    },
    {
      "url": "https://www.amazon.com/dp/B0878NVLX7/ref=twister_B0878ZHGQQ",
      "id": "B0878NVLX7"
    },
    {
      "url": "https://www.amazon.com/dp/B0878QZQN9/ref=twister_B0878ZHGQQ",
      "id": "B0878QZQN9"
    },
    {
      "url": "https://www.amazon.com/dp/B0B8DCXRGZ/ref=twister_B0878ZHGQQ",
      "id": "B0B8DCXRGZ"
    },
    {
      "url": "https://www.amazon.com/dp/B0B8DHGHX9/ref=twister_B0878ZHGQQ",
      "id": "B0B8DHGHX9"
    },
    {
      "url": "https://www.amazon.com/dp/B0B8DJHZLG/ref=twister_B0878ZHGQQ",
      "id": "B0B8DJHZLG"
    },
    {
      "url": "https://www.amazon.com/dp/B08JH494HN/ref=twister_B0878ZHGQQ",
      "id": "B08JH494HN"
    }
  ]
}