{
  "id": "B0BG8YCNZM",
  "title": "Reebok Men's Club MEMT Casual Sneakers",
  "description": null,
  "images": [
    [
      "https://m.media-amazon.com/images/I/61kuVNUAi4L._AC_UX625_.jpg",
      "https://m.media-amazon.com/images/I/61kuVNUAi4L._AC_UX535_.jpg",
      "https://m.media-amazon.com/images/I/61kuVNUAi4L._AC_UX575_.jpg",
      "https://m.media-amazon.com/images/I/61kuVNUAi4L._AC_UX500_.jpg",
      "https://m.media-amazon.com/images/I/61kuVNUAi4L._AC_UX675_.jpg",
      "https://m.media-amazon.com/images/I/61kuVNUAi4L._AC_UX395_.jpg",
      "https://m.media-amazon.com/images/I/61kuVNUAi4L._AC_UX695_.jpg"
    ]
  ],
  "rating": 4.5,
  "reviews_count": 8443,
  "reviews_link": "https://www.amazon.com/Reebok-Mens-Club-Casual-Sneakers/product-reviews/B0BG8YCNZM/ref=cm_cr_dp_d_show_all_btm?ie=UTF8&reviewerType=all_reviews",
  "price_range": {
    "from": 42.25,
    "to": 95.95
  },
  "variants": [
    {
      "url": "https://www.amazon.com/dp/B07VVTVN45/ref=twister_B0BG8YCNZM",
      "id": "B07VVTVN45"
    },
    {
      "url": "https://www.amazon.com/dp/B07W38WVCQ/ref=twister_B0BG8YCNZM",
      "id": "B07W38WVCQ"
    },
    {
      "url": "https://www.amazon.com/dp/B07W576XB1/ref=twister_B0BG8YCNZM",
      "id": "B07W576XB1"
    },
    {
      "url": "https://www.amazon.com/dp/B07MV5R2BC/ref=twister_B0BG8YCNZM",
      "id": "B07MV5R2BC"
    },
    {
      "url": "https://www.amazon.com/dp/B07VXZ8TP4/ref=twister_B0BG8YCNZM",
      "id": "B07VXZ8TP4"
    },
    {
      "url": "https://www.amazon.com/dp/B00RW1J17I/ref=twister_B0BG8YCNZM",
      "id": "B00RW1J17I"
    }
  ]
}